survivaldnn/__init__.py
survivaldnn/losses.py
survivaldnn/main.py
survivaldnn-1.0.1.dist-info/licenses/LICENSE
survivaldnn-1.0.1.dist-info/METADATA
survivaldnn-1.0.1.dist-info/WHEEL
survivaldnn-1.0.1.dist-info/top_level.txt
survivaldnn-1.0.1.dist-info/RECORD
