Metadata-Version: 2.4
Name: SurvivalDNN
Version: 1.0.1
Summary: Survival Analysis using Deep Learning for Prediction
Home-page: https://github.com/adamvvu/SurvivalDNN
Author: Adam Wu
Author-email: adamwu1@outlook.com
License: MIT License
Project-URL: homepage, https://github.com/adamvvu/survivaldnn
Project-URL: documentation, https://github.com/adamvvu/survivaldnn
Project-URL: repository, https://github.com/adamvvu/survivaldnn
Classifier: Intended Audience :: Science/Research
Classifier: Topic :: Scientific/Engineering :: Information Analysis
Classifier: Programming Language :: Python :: 3
Classifier: Operating System :: OS Independent
Classifier: License :: OSI Approved :: MIT License
Requires-Python: >=3.9
License-File: LICENSE
Requires-Dist: numpy
Requires-Dist: pandas
Requires-Dist: tensorflow>=2.10
Requires-Dist: tf-compactprogbar
Requires-Dist: matplotlib
Dynamic: home-page
Dynamic: license-file
Dynamic: requires-python
